{
  "id": "stanford-sd580gh8365",
  "dct_title_s": "Wassende graadt kaert vande GROOTE, ZUYD, ZEE. van Ilhas d'Ladrones, Tot Rio de la Plate",
  "dct_description_sm": [
    "See general notes.",
    "Reissued, 1686 and later with \"Gedrucht Bÿ J:Robyn. met Previlegio\".",
    "L.C. 493; Koeman IV,Rob1(20); KoemanIV,Rob4(50).",
    "Issued in his: Zee, Zea-atlas-aquatique, del mar. -- Amsterdam, 1683.",
    "California as large island on second Sanson model, with coastal place names. \"Straet Anian\" to north. Nearly identical with Van Keulen's 1680 map entitled \"Pascaert vande Zuyd Zee en een gedeelte van Brazil...\" Same cartouche with minor changes made, America labelled \"America Pars\",\"Staten Landt\" [New Zealand] to far southwest, and \"Compagnies Landt\" to far northwest.",
    "\"Gedruckt Bÿ J:Robyn. met Previlegio\""
  ],
  "dct_creator_sm": [
    "Robijn, Jacobus, d. ca. 1710."
  ],
  "dct_subject_sm": [
    "California as an island--Maps",
    "Pacific Ocean--Maps"
  ],
  "dcat_theme_sm": [
    "Imagery"
  ],
  "schema_provider_s": "Stanford",
  "dct_identifier_sm": [
    "https://purl.stanford.edu/sd580gh8365",
    "88",
    "88-02"
  ],
  "gbl_georeferenced_b": false,
  "gbl_resourceClass_sm": [
    "Maps"
  ],
  "dct_format_s": "JPEG2000",
  "locn_geometry": "ENVELOPE(-160.0, 20.0, 90.0, -90.0)",
  "dcat_bbox": "ENVELOPE(-160.0, 20.0, 90.0, -90.0)",
  "pcdm_memberOf_sm": [
    "stanford-zb871zd0767"
  ],
  "dct_rights_sm": [
    "Image from the Glen McLaughlin Map Collection of California as an Island courtesy Stanford University Libraries. This item is in the public domain. There are no restrictions on use. If you have questions, please contact the David Rumsey Map Center at rumseymapcenter@stanford.edu."
  ],
  "dct_rightsHolder_sm": [
    "This work has been identified as being free of known restrictions under copyright law, including all related and neighboring rights. You can copy, modify, distribute and perform the work, even for commercial purposes, all without asking permission."
  ],
  "dct_license_sm": [
    "https://creativecommons.org/publicdomain/mark/1.0/"
  ],
  "dct_accessRights_s": "Public",
  "gbl_mdModified_dt": "2024-06-13T06:28:10Z",
  "gbl_mdVersion_s": "Aardvark",
  "dct_references_s": "{\"http://schema.org/url\":\"https://purl.stanford.edu/sd580gh8365\",\"http://schema.org/downloadUrl\":[{\"url\":\"https://stacks.stanford.edu/object/sd580gh8365\",\"label\":\"Zipped object\"}],\"https://oembed.com\":\"https://purl.stanford.edu/embed.json?hide_title=true\\u0026url=https%3A%2F%2Fpurl.stanford.edu%2Fsd580gh8365\",\"http://iiif.io/api/presentation#manifest\":\"https://purl.stanford.edu/sd580gh8365/iiif3/manifest\",\"https://schema.org/relatedLink\":\"https://searchworks.stanford.edu/view/a10625074\"}"
}
