{
  "geoblacklight_version": "1.0",
  "dc_identifier_s": "http://purl.stanford.edu/fg387cp9930",
  "dc_title_s": "Inland Waters, Sri Lanka, 2013",
  "dc_description_s": "This polygon shapefile represents areas of inland water in Sri Lanka. The Global Map Sri Lanka version 2 was developed based on Global Map Specifications version 2.2. The data source of Boundary layer was a 1:250,000 map image made in 2012. The data source of Drainage was a 1:250,000 map image made in 1996 and 2008.Only capital area is updated from ALOS stellite images of 2010-2011. The data source of Population Center layer was a 1:250,000 map image made in 1996 and 2008. The data source of Transportation layer was a 1:250,000 map image made in 2012. Only capital area is updated from ALOS stellite images of 2010-2011.Global Map data were developed under the cooperation of National Geospatial Information Authorities (NGIAs) of respective countries and regions.",
  "dc_rights_s": "Public",
  "dct_provenance_s": "Stanford",
  "dct_references_s": "{\"http://schema.org/url\":\"http://purl.stanford.edu/fg387cp9930\",\"http://schema.org/downloadUrl\":\"https://stacks.stanford.edu/file/druid:fg387cp9930/data.zip\",\"http://www.loc.gov/mods/v3\":\"http://purl.stanford.edu/fg387cp9930.mods\",\"http://www.isotc211.org/schemas/2005/gmd/\":\"https://raw.githubusercontent.com/OpenGeoMetadata/edu.stanford.purl/master/fg/387/cp/9930/iso19139.xml\",\"http://www.opengis.net/def/serviceType/ogc/wfs\":\"https://geowebservices.stanford.edu/geoserver/wfs\",\"http://www.opengis.net/def/serviceType/ogc/wms\":\"https://geowebservices.stanford.edu/geoserver/wms\"}",
  "layer_id_s": "druid:fg387cp9930",
  "layer_slug_s": "stanford-fg387cp9930",
  "layer_geom_type_s": "Polygon",
  "layer_modified_dt": "2018-06-10T15:04:35Z",
  "dc_format_s": "Shapefile",
  "dc_language_s": "English",
  "dc_type_s": "Dataset",
  "dc_publisher_s": "International Steering Committee for Global Mapping",
  "dc_creator_sm": [
    "International Steering Committee for Global Mapping",
    "Sri Lanka. Minindōru Depārtamēntuva"
  ],
  "dc_subject_sm": [
    "Bodies of water",
    "Inland Waters"
  ],
  "dct_issued_s": "2013",
  "dct_temporal_sm": [
    "2013"
  ],
  "dct_spatial_sm": [
    "Sri Lanka"
  ],
  "solr_geom": "ENVELOPE(79.788612, 81.864782, 9.459422, 5.998288)",
  "solr_year_i": 2013,
  "stanford_rights_metadata_s": "<?xml version=\"1.0\"?>\n<rightsMetadata>\n   <access type=\"discover\">\n      <machine>\n         <world/>\n      </machine>\n   </access>\n   <access type=\"read\">\n      <machine>\n         <world/>\n      </machine>\n   </access>\n   <use>\n      <human type=\"useAndReproduction\">This dataset is freely available for academic use and other non-commercial use. Redistribution, or commercial use is not allowed without prior permission. You are free to create maps and use the data in other ways for publication in academic journals, books, reports, etc.</human>\n   </use>\n</rightsMetadata>\n"
}