{
  "id": "stanford-jq618sp8021",
  "dct_title_s": "Protected Areas Database of the United States (PAD-US)",
  "dct_description_sm": [
    "The Gap Analysis Program (GAP) is an element of the U.S. Geological Survey. This collection of data contains shapefiles relating to the location, ownership, and stewardship of protected areas within the United States.",
    "Title supplied by cataloger. Website accessed: March 31, 2017.",
    "System requirements: Geographic Information Systems (GIS) software that reads ESRI shapefile format."
  ],
  "dct_language_sm": [
    "eng"
  ],
  "dct_publisher_sm": [
    "Gap Analysis Program (U.S.)"
  ],
  "dct_subject_sm": [
    "Open spaces",
    "Marine parks and reserves",
    "Marine resources conservation"
  ],
  "dct_spatial_sm": [
    "United States"
  ],
  "schema_provider_s": "Stanford",
  "dct_identifier_sm": [
    "https://purl.stanford.edu/jq618sp8021"
  ],
  "gbl_georeferenced_b": false,
  "gbl_resourceClass_sm": [
    "Collections"
  ],
  "locn_geometry": "ENVELOPE(-64.35, 144.4, 71.6, -14.75)",
  "dcat_bbox": "ENVELOPE(-64.35, 144.4, 71.6, -14.75)",
  "dct_rights_sm": [
    "This item is in the public domain.  There are no restrictions on use."
  ],
  "dct_rightsHolder_sm": [
    "This work is in the Public Domain, meaning that it is not subject to copyright."
  ],
  "dct_accessRights_s": "Public",
  "gbl_mdModified_dt": "2011-04-29T00:00:00Z",
  "gbl_mdVersion_s": "Aardvark",
  "dct_references_s": "{\"http://schema.org/url\":\"https://purl.stanford.edu/jq618sp8021\",\"https://schema.org/relatedLink\":\"https://searchworks.stanford.edu/view/a11961902\"}"
}
