{
  "uuid": "http://purl.stanford.edu/tp856vy3579",
  "dc_identifier_s": "http://purl.stanford.edu/tp856vy3579",
  "dc_title_s": "Fire Regime and Condition Class: San Francisco Bay Area, California, 2003",
  "dc_description_s": "Wildfire can cause serious and long-lasting damage to ecosystems. Following National Fire Plan concepts, this raster dataset depicts the California Department of Forestry and Fire Protection Fire Resource and Protection Program's (FRAP) use of data specific to the nine county San Francisco Bay Area Region, California to describe ecosystems and fire-related metrics used in other analyses to define and describe fire-related risks to ecosystems. Fundamental to this idea is that current expected fires are compared to historic fire regimes with respect to fire frequency, size, patchiness and effects on key ecosystem elements and processes. Thus, these classes are then assigned based on current vegetation type and structure, an understanding of its pre-settlement fire regime and current conditions regarding expected fire frequency and potential fire behavior. As a result of these efforts, Condition Classes were defined as the “relative risk of losing key components that define an ecosystem\" (Hardy et al., 2001). Source data was compiled by the California Department of Forestry and Fire Protection. This dataset was developed/compiled for use in the San Francisco Bay Area Upland Habitat Goals Project, a Project used to identify a Conservation Lands Network (CLN) for biodiversity preservation to inform conservation investments and lasting cooperative conservation partnerships. The Conservation Lands Network GIS Database is the primary output of the Project. The data depicts the spatially explicit CLN that is recommended for the nine county San Francisco Bay Area Region, California.",
  "dc_rights_s": "Public",
  "dct_provenance_s": "Stanford",
  "dct_references_s": "{\"http://schema.org/url\":\"http://purl.stanford.edu/tp856vy3579\",\"http://schema.org/downloadUrl\":\"http://stacks.stanford.edu/file/druid:tp856vy3579/data.zip\",\"http://www.loc.gov/mods/v3\":\"http://purl.stanford.edu/tp856vy3579.mods\",\"http://www.isotc211.org/schemas/2005/gmd/\":\"http://opengeometadata.stanford.edu/metadata/edu.stanford.purl/druid:tp856vy3579/iso19139.xml\",\"http://www.w3.org/1999/xhtml\":\"http://opengeometadata.stanford.edu/metadata/edu.stanford.purl/druid:tp856vy3579/default.html\",\"http://www.opengis.net/def/serviceType/ogc/wcs\":\"https://geowebservices.stanford.edu/geoserver/wcs\",\"http://www.opengis.net/def/serviceType/ogc/wms\":\"https://geowebservices.stanford.edu/geoserver/wms\"}",
  "layer_id_s": "druid:tp856vy3579",
  "layer_slug_s": "stanford-tp856vy3579",
  "layer_geom_type_s": "Raster",
  "layer_modified_dt": "2017-01-07T00:45:29Z",
  "dc_format_s": "ArcGRID",
  "dc_language_s": "English",
  "dc_type_s": "Dataset",
  "dc_publisher_s": "Bay Area Open Space Council",
  "dc_creator_sm": [
    "Bay Area Open Space Council",
    "Conservation Lands Network",
    "San Francisco Bay Area Upland Habitat Goals Project",
    "GreenInfo Network (Firm)"
  ],
  "dc_subject_sm": [
    "Biogeography",
    "Ecosystem health",
    "Forest resilience",
    "Ecological disturbances",
    "Forests and forestry",
    "Timber",
    "Forest fires",
    "Forest fire forecasting",
    "Fire risk assessment",
    "Ecological risk assessment",
    "Environmental impact analysis",
    "Imagery and Base Maps",
    "Geoscientific Information"
  ],
  "dct_issued_s": "2011",
  "dct_temporal_sm": "2004",
  "dct_spatial_sm": [
    "San Francisco Bay Area (Calif.)",
    "Alameda County (Calif.)",
    "Contra Costa County (Calif.)",
    "Marin County (Calif.)",
    "Napa County (Calif.)",
    "San Francisco County (Calif.)",
    "San Mateo County (Calif.)",
    "Santa Clara County (Calif.)",
    "Solano County (Calif.)",
    "Sonoma County (Calif.)"
  ],
  "dc_relation_sm": [
    "http://sws.geonames.org/5322745/",
    "http://sws.geonames.org/5339268/",
    "http://sws.geonames.org/5370468/",
    "http://sws.geonames.org/5376101/",
    "http://sws.geonames.org/5392427/",
    "http://sws.geonames.org/5393021/",
    "http://sws.geonames.org/5396987/",
    "http://sws.geonames.org/5397100/"
  ],
  "georss_box_s": "36.8532505 -123.5362996 38.8854811 -121.2042819",
  "georss_polygon_s": "36.8532505 -123.5362996 38.8854811 -123.5362996 38.8854811 -121.2042819 36.8532505 -121.2042819 36.8532505 -123.5362996",
  "solr_geom": "ENVELOPE(-123.5362996, -121.2042819, 38.8854811, 36.8532505)",
  "solr_year_i": 2004,
  "stanford_rights_metadata_s": "<?xml version=\"1.0\"?>\n<rightsMetadata>\n  <access type=\"discover\">\n    <machine>\n      <world/>\n    </machine>\n  </access>\n  <access type=\"read\">\n    <machine>\n      <world/>\n    </machine>\n  </access>\n  <use>\n    <human type=\"useAndReproduction\">This item is in the public domain.  There are no restrictions on use.</human>\n    <human type=\"creativeCommons\"/>\n    <machine type=\"creativeCommons\"/>\n  </use>\n  <copyright>\n    <human>This work is in the Public Domain, meaning that it is not subject to copyright.</human>\n  </copyright>\n</rightsMetadata>\n"
}