<?xml version="1.0" encoding="utf-8"?>
<gfc:FC_FeatureCatalogue xmlns:xsi="http://www.w3.org/2001/XMLSchema-instance" xmlns:gco="http://www.isotc211.org/2005/gco" xmlns:gfc="http://www.isotc211.org/2005/gfc" xmlns:gmd="http://www.isotc211.org/2005/gmd" xmlns:gmx="http://www.isotc211.org/2005/gmx" xmlns:gml="http://www.opengis.net/gml/3.2" xmlns:xlink="http://www.w3.org/1999/xlink" xmlns="http://www.isotc211.org/2005/gfc" xsi:schemaLocation="http://www.isotc211.org/2005/gfc http://www.isotc211.org/2005/gfc/gfc.xsd" uuid="c47b4dfc-4769-422e-8d73-1f67bf67a43b">
  <gmx:name>
    <gco:CharacterString>Entity and Attribute Information</gco:CharacterString>
  </gmx:name>
  <gmx:scope>
    <gco:CharacterString>Buildings</gco:CharacterString>
  </gmx:scope>
  <gmx:versionNumber gco:nilReason="unknown"/>
  <gmx:versionDate>
    <gco:Date>2022</gco:Date>
  </gmx:versionDate>
  <gmx:language>
    <gco:CharacterString>eng; US</gco:CharacterString>
  </gmx:language>
  <gmx:characterSet>
    <gmd:MD_CharacterSetCode codeList="http://www.isotc211.org/2005/resources/Codelist/gmxCodelists.xml#MD_CharacterSetCode" codeListValue="utf8" codeSpace="ISOTC211/19115"/>
  </gmx:characterSet>
  <gfc:featureType>
    <gfc:FC_FeatureType>
      <gfc:typeName>
        <gco:LocalName>Buildings</gco:LocalName>
      </gfc:typeName>
      <gfc:definition/>
      <gfc:isAbstract>
        <gco:Boolean>false</gco:Boolean>
      </gfc:isAbstract>
      <gfc:featureCatalogue uuidref="c47b4dfc-4769-422e-8d73-1f67bf67a43b"/>
      <gfc:carrierOfCharacteristics>
        <gfc:FC_FeatureAttribute>
          <gfc:memberName>
            <gco:LocalName>FID</gco:LocalName>
          </gfc:memberName>
          <gfc:definition>
            <gco:CharacterString>Internal feature number.</gco:CharacterString>
          </gfc:definition>
          <gfc:cardinality gco:nilReason="unknown"/>
          <gfc:definitionReference>
            <gfc:FC_DefinitionReference>
              <gfc:definitionSource>
                <gfc:FC_DefinitionSource>
                  <gfc:source>
                    <gmd:CI_Citation>
                      <gmd:title>
                        <gco:CharacterString>Esri</gco:CharacterString>
                      </gmd:title>
                      <gmd:date gco:nilReason="unknown"/>
                      <gmd:citedResponsibleParty>
                        <gmd:CI_ResponsibleParty>
                          <gmd:organisationName>
                            <gco:CharacterString>Esri</gco:CharacterString>
                          </gmd:organisationName>
                          <gmd:role>
                            <gmd:CI_RoleCode codeList="http://www.isotc211.org/2005/resources/Codelist/gmxCodelists.xml#CI_RoleCode" codeListValue="resourceProvider" codeSpace="001"/>
                          </gmd:role>
                        </gmd:CI_ResponsibleParty>
                      </gmd:citedResponsibleParty>
                    </gmd:CI_Citation>
                  </gfc:source>
                </gfc:FC_DefinitionSource>
              </gfc:definitionSource>
            </gfc:FC_DefinitionReference>
          </gfc:definitionReference>
          <gfc:valueType>
            <gco:TypeName>
              <gco:aName>
                <gco:CharacterString>OID</gco:CharacterString>
              </gco:aName>
            </gco:TypeName>
          </gfc:valueType>
        </gfc:FC_FeatureAttribute>
      </gfc:carrierOfCharacteristics>
      <gfc:carrierOfCharacteristics>
        <gfc:FC_FeatureAttribute>
          <gfc:memberName>
            <gco:LocalName>Shape</gco:LocalName>
          </gfc:memberName>
          <gfc:definition>
            <gco:CharacterString>Feature geometry.</gco:CharacterString>
          </gfc:definition>
          <gfc:cardinality gco:nilReason="unknown"/>
          <gfc:definitionReference>
            <gfc:FC_DefinitionReference>
              <gfc:definitionSource>
                <gfc:FC_DefinitionSource>
                  <gfc:source>
                    <gmd:CI_Citation>
                      <gmd:title>
                        <gco:CharacterString>Esri</gco:CharacterString>
                      </gmd:title>
                      <gmd:date gco:nilReason="unknown"/>
                      <gmd:citedResponsibleParty>
                        <gmd:CI_ResponsibleParty>
                          <gmd:organisationName>
                            <gco:CharacterString>Esri</gco:CharacterString>
                          </gmd:organisationName>
                          <gmd:role>
                            <gmd:CI_RoleCode codeList="http://www.isotc211.org/2005/resources/Codelist/gmxCodelists.xml#CI_RoleCode" codeListValue="resourceProvider" codeSpace="001"/>
                          </gmd:role>
                        </gmd:CI_ResponsibleParty>
                      </gmd:citedResponsibleParty>
                    </gmd:CI_Citation>
                  </gfc:source>
                </gfc:FC_DefinitionSource>
              </gfc:definitionSource>
            </gfc:FC_DefinitionReference>
          </gfc:definitionReference>
          <gfc:valueType>
            <gco:TypeName>
              <gco:aName>
                <gco:CharacterString>Geometry</gco:CharacterString>
              </gco:aName>
            </gco:TypeName>
          </gfc:valueType>
        </gfc:FC_FeatureAttribute>
      </gfc:carrierOfCharacteristics>
      <gfc:carrierOfCharacteristics>
        <gfc:FC_FeatureAttribute>
          <gfc:memberName>
            <gco:LocalName>OBJECTID</gco:LocalName>
          </gfc:memberName>
          <gfc:definition>
            <gco:CharacterString>Identifier of the digital object (building)</gco:CharacterString>
          </gfc:definition>
          <gfc:cardinality gco:nilReason="unknown"/>
          <gfc:valueType>
            <gco:TypeName>
              <gco:aName>
                <gco:CharacterString>Integer</gco:CharacterString>
              </gco:aName>
            </gco:TypeName>
          </gfc:valueType>
        </gfc:FC_FeatureAttribute>
      </gfc:carrierOfCharacteristics>
      <gfc:carrierOfCharacteristics>
        <gfc:FC_FeatureAttribute>
          <gfc:memberName>
            <gco:LocalName>IDBAT</gco:LocalName>
          </gfc:memberName>
          <gfc:definition>
            <gco:CharacterString>Identifier of the building (Virtual Shanghai)</gco:CharacterString>
          </gfc:definition>
          <gfc:cardinality gco:nilReason="unknown"/>
          <gfc:valueType>
            <gco:TypeName>
              <gco:aName>
                <gco:CharacterString>Double</gco:CharacterString>
              </gco:aName>
            </gco:TypeName>
          </gfc:valueType>
        </gfc:FC_FeatureAttribute>
      </gfc:carrierOfCharacteristics>
      <gfc:carrierOfCharacteristics>
        <gfc:FC_FeatureAttribute>
          <gfc:memberName>
            <gco:LocalName>NAME</gco:LocalName>
          </gfc:memberName>
          <gfc:definition>
            <gco:CharacterString>Name of the bulding in English or French or Pinyin</gco:CharacterString>
          </gfc:definition>
          <gfc:cardinality gco:nilReason="unknown"/>
          <gfc:valueType>
            <gco:TypeName>
              <gco:aName>
                <gco:CharacterString>String</gco:CharacterString>
              </gco:aName>
            </gco:TypeName>
          </gfc:valueType>
        </gfc:FC_FeatureAttribute>
      </gfc:carrierOfCharacteristics>
      <gfc:carrierOfCharacteristics>
        <gfc:FC_FeatureAttribute>
          <gfc:memberName>
            <gco:LocalName>GEOCODAGE</gco:LocalName>
          </gfc:memberName>
          <gfc:definition>
            <gco:CharacterString>Confirmation of geocoding</gco:CharacterString>
          </gfc:definition>
          <gfc:cardinality gco:nilReason="unknown"/>
          <gfc:valueType>
            <gco:TypeName>
              <gco:aName>
                <gco:CharacterString>String</gco:CharacterString>
              </gco:aName>
            </gco:TypeName>
          </gfc:valueType>
        </gfc:FC_FeatureAttribute>
      </gfc:carrierOfCharacteristics>
      <gfc:carrierOfCharacteristics>
        <gfc:FC_FeatureAttribute>
          <gfc:memberName>
            <gco:LocalName>F_ADDRESS</gco:LocalName>
          </gfc:memberName>
          <gfc:definition>
            <gco:CharacterString>Full address of the building</gco:CharacterString>
          </gfc:definition>
          <gfc:cardinality gco:nilReason="unknown"/>
          <gfc:valueType>
            <gco:TypeName>
              <gco:aName>
                <gco:CharacterString>String</gco:CharacterString>
              </gco:aName>
            </gco:TypeName>
          </gfc:valueType>
        </gfc:FC_FeatureAttribute>
      </gfc:carrierOfCharacteristics>
      <gfc:carrierOfCharacteristics>
        <gfc:FC_FeatureAttribute>
          <gfc:memberName>
            <gco:LocalName>CHINESE</gco:LocalName>
          </gfc:memberName>
          <gfc:definition>
            <gco:CharacterString>Name of the bulding in Chinese</gco:CharacterString>
          </gfc:definition>
          <gfc:cardinality gco:nilReason="unknown"/>
          <gfc:valueType>
            <gco:TypeName>
              <gco:aName>
                <gco:CharacterString>String</gco:CharacterString>
              </gco:aName>
            </gco:TypeName>
          </gfc:valueType>
        </gfc:FC_FeatureAttribute>
      </gfc:carrierOfCharacteristics>
      <gfc:carrierOfCharacteristics>
        <gfc:FC_FeatureAttribute>
          <gfc:memberName>
            <gco:LocalName>START</gco:LocalName>
          </gfc:memberName>
          <gfc:definition>
            <gco:CharacterString>Date of construction (work completed)</gco:CharacterString>
          </gfc:definition>
          <gfc:cardinality gco:nilReason="unknown"/>
          <gfc:valueType>
            <gco:TypeName>
              <gco:aName>
                <gco:CharacterString>Integer</gco:CharacterString>
              </gco:aName>
            </gco:TypeName>
          </gfc:valueType>
        </gfc:FC_FeatureAttribute>
      </gfc:carrierOfCharacteristics>
      <gfc:carrierOfCharacteristics>
        <gfc:FC_FeatureAttribute>
          <gfc:memberName>
            <gco:LocalName>END_</gco:LocalName>
          </gfc:memberName>
          <gfc:cardinality gco:nilReason="unknown"/>
          <gfc:valueType>
            <gco:TypeName>
              <gco:aName>
                <gco:CharacterString>Integer</gco:CharacterString>
              </gco:aName>
            </gco:TypeName>
          </gfc:valueType>
        </gfc:FC_FeatureAttribute>
      </gfc:carrierOfCharacteristics>
      <gfc:carrierOfCharacteristics>
        <gfc:FC_FeatureAttribute>
          <gfc:memberName>
            <gco:LocalName>TYP01</gco:LocalName>
          </gfc:memberName>
          <gfc:definition>
            <gco:CharacterString>Level 1 of the building typology (Virtual Shanghai)</gco:CharacterString>
          </gfc:definition>
          <gfc:cardinality gco:nilReason="unknown"/>
          <gfc:valueType>
            <gco:TypeName>
              <gco:aName>
                <gco:CharacterString>String</gco:CharacterString>
              </gco:aName>
            </gco:TypeName>
          </gfc:valueType>
        </gfc:FC_FeatureAttribute>
      </gfc:carrierOfCharacteristics>
      <gfc:carrierOfCharacteristics>
        <gfc:FC_FeatureAttribute>
          <gfc:memberName>
            <gco:LocalName>TYP02</gco:LocalName>
          </gfc:memberName>
          <gfc:definition>
            <gco:CharacterString>Level 2 of the building typology (Virtual Shanghai)</gco:CharacterString>
          </gfc:definition>
          <gfc:cardinality gco:nilReason="unknown"/>
          <gfc:valueType>
            <gco:TypeName>
              <gco:aName>
                <gco:CharacterString>String</gco:CharacterString>
              </gco:aName>
            </gco:TypeName>
          </gfc:valueType>
        </gfc:FC_FeatureAttribute>
      </gfc:carrierOfCharacteristics>
      <gfc:carrierOfCharacteristics>
        <gfc:FC_FeatureAttribute>
          <gfc:memberName>
            <gco:LocalName>TYP03</gco:LocalName>
          </gfc:memberName>
          <gfc:definition>
            <gco:CharacterString>Level 3 of the building typology (Virtual Shanghai)</gco:CharacterString>
          </gfc:definition>
          <gfc:cardinality gco:nilReason="unknown"/>
          <gfc:valueType>
            <gco:TypeName>
              <gco:aName>
                <gco:CharacterString>String</gco:CharacterString>
              </gco:aName>
            </gco:TypeName>
          </gfc:valueType>
        </gfc:FC_FeatureAttribute>
      </gfc:carrierOfCharacteristics>
      <gfc:carrierOfCharacteristics>
        <gfc:FC_FeatureAttribute>
          <gfc:memberName>
            <gco:LocalName>TYP04</gco:LocalName>
          </gfc:memberName>
          <gfc:definition>
            <gco:CharacterString>Level 4 of the building typology (Virtual Shanghai)</gco:CharacterString>
          </gfc:definition>
          <gfc:cardinality gco:nilReason="unknown"/>
          <gfc:valueType>
            <gco:TypeName>
              <gco:aName>
                <gco:CharacterString>String</gco:CharacterString>
              </gco:aName>
            </gco:TypeName>
          </gfc:valueType>
        </gfc:FC_FeatureAttribute>
      </gfc:carrierOfCharacteristics>
      <gfc:carrierOfCharacteristics>
        <gfc:FC_FeatureAttribute>
          <gfc:memberName>
            <gco:LocalName>TYP05</gco:LocalName>
          </gfc:memberName>
          <gfc:definition>
            <gco:CharacterString>Level 5 of the building typology (Virtual Shanghai)</gco:CharacterString>
          </gfc:definition>
          <gfc:cardinality gco:nilReason="unknown"/>
          <gfc:valueType>
            <gco:TypeName>
              <gco:aName>
                <gco:CharacterString>String</gco:CharacterString>
              </gco:aName>
            </gco:TypeName>
          </gfc:valueType>
        </gfc:FC_FeatureAttribute>
      </gfc:carrierOfCharacteristics>
      <gfc:carrierOfCharacteristics>
        <gfc:FC_FeatureAttribute>
          <gfc:memberName>
            <gco:LocalName>TYP06</gco:LocalName>
          </gfc:memberName>
          <gfc:definition>
            <gco:CharacterString>Level 6 of the building typology (Virtual Shanghai)</gco:CharacterString>
          </gfc:definition>
          <gfc:cardinality gco:nilReason="unknown"/>
          <gfc:valueType>
            <gco:TypeName>
              <gco:aName>
                <gco:CharacterString>String</gco:CharacterString>
              </gco:aName>
            </gco:TypeName>
          </gfc:valueType>
        </gfc:FC_FeatureAttribute>
      </gfc:carrierOfCharacteristics>
      <gfc:carrierOfCharacteristics>
        <gfc:FC_FeatureAttribute>
          <gfc:memberName>
            <gco:LocalName>TYP07</gco:LocalName>
          </gfc:memberName>
          <gfc:definition>
            <gco:CharacterString>Level 7 of the building typology (Virtual Shanghai)</gco:CharacterString>
          </gfc:definition>
          <gfc:cardinality gco:nilReason="unknown"/>
          <gfc:valueType>
            <gco:TypeName>
              <gco:aName>
                <gco:CharacterString>String</gco:CharacterString>
              </gco:aName>
            </gco:TypeName>
          </gfc:valueType>
        </gfc:FC_FeatureAttribute>
      </gfc:carrierOfCharacteristics>
      <gfc:carrierOfCharacteristics>
        <gfc:FC_FeatureAttribute>
          <gfc:memberName>
            <gco:LocalName>TYP08</gco:LocalName>
          </gfc:memberName>
          <gfc:definition>
            <gco:CharacterString>Level 8 of the building typology (Virtual Shanghai)</gco:CharacterString>
          </gfc:definition>
          <gfc:cardinality gco:nilReason="unknown"/>
          <gfc:valueType>
            <gco:TypeName>
              <gco:aName>
                <gco:CharacterString>String</gco:CharacterString>
              </gco:aName>
            </gco:TypeName>
          </gfc:valueType>
        </gfc:FC_FeatureAttribute>
      </gfc:carrierOfCharacteristics>
      <gfc:carrierOfCharacteristics>
        <gfc:FC_FeatureAttribute>
          <gfc:memberName>
            <gco:LocalName>TYP09</gco:LocalName>
          </gfc:memberName>
          <gfc:definition>
            <gco:CharacterString>Level 9 of the building typology (Virtual Shanghai)</gco:CharacterString>
          </gfc:definition>
          <gfc:cardinality gco:nilReason="unknown"/>
          <gfc:valueType>
            <gco:TypeName>
              <gco:aName>
                <gco:CharacterString>String</gco:CharacterString>
              </gco:aName>
            </gco:TypeName>
          </gfc:valueType>
        </gfc:FC_FeatureAttribute>
      </gfc:carrierOfCharacteristics>
      <gfc:carrierOfCharacteristics>
        <gfc:FC_FeatureAttribute>
          <gfc:memberName>
            <gco:LocalName>TYP10</gco:LocalName>
          </gfc:memberName>
          <gfc:definition>
            <gco:CharacterString>Level 10 of the building typology (Virtual Shanghai)</gco:CharacterString>
          </gfc:definition>
          <gfc:cardinality gco:nilReason="unknown"/>
          <gfc:valueType>
            <gco:TypeName>
              <gco:aName>
                <gco:CharacterString>String</gco:CharacterString>
              </gco:aName>
            </gco:TypeName>
          </gfc:valueType>
        </gfc:FC_FeatureAttribute>
      </gfc:carrierOfCharacteristics>
      <gfc:carrierOfCharacteristics>
        <gfc:FC_FeatureAttribute>
          <gfc:memberName>
            <gco:LocalName>TYP11</gco:LocalName>
          </gfc:memberName>
          <gfc:definition>
            <gco:CharacterString>Level 11 of the building typology (Virtual Shanghai)</gco:CharacterString>
          </gfc:definition>
          <gfc:cardinality gco:nilReason="unknown"/>
          <gfc:valueType>
            <gco:TypeName>
              <gco:aName>
                <gco:CharacterString>String</gco:CharacterString>
              </gco:aName>
            </gco:TypeName>
          </gfc:valueType>
        </gfc:FC_FeatureAttribute>
      </gfc:carrierOfCharacteristics>
      <gfc:carrierOfCharacteristics>
        <gfc:FC_FeatureAttribute>
          <gfc:memberName>
            <gco:LocalName>XC</gco:LocalName>
          </gfc:memberName>
          <gfc:definition>
            <gco:CharacterString>X coordinates </gco:CharacterString>
          </gfc:definition>
          <gfc:cardinality gco:nilReason="unknown"/>
          <gfc:valueType>
            <gco:TypeName>
              <gco:aName>
                <gco:CharacterString>Double</gco:CharacterString>
              </gco:aName>
            </gco:TypeName>
          </gfc:valueType>
        </gfc:FC_FeatureAttribute>
      </gfc:carrierOfCharacteristics>
      <gfc:carrierOfCharacteristics>
        <gfc:FC_FeatureAttribute>
          <gfc:memberName>
            <gco:LocalName>YC</gco:LocalName>
          </gfc:memberName>
          <gfc:definition>
            <gco:CharacterString>Y coordinates</gco:CharacterString>
          </gfc:definition>
          <gfc:cardinality gco:nilReason="unknown"/>
          <gfc:valueType>
            <gco:TypeName>
              <gco:aName>
                <gco:CharacterString>Double</gco:CharacterString>
              </gco:aName>
            </gco:TypeName>
          </gfc:valueType>
        </gfc:FC_FeatureAttribute>
      </gfc:carrierOfCharacteristics>
      <gfc:carrierOfCharacteristics>
        <gfc:FC_FeatureAttribute>
          <gfc:memberName>
            <gco:LocalName>DATE_CREAT</gco:LocalName>
          </gfc:memberName>
          <gfc:definition>
            <gco:CharacterString>Date of creation of the digital object (building)</gco:CharacterString>
          </gfc:definition>
          <gfc:cardinality gco:nilReason="unknown"/>
          <gfc:valueType>
            <gco:TypeName>
              <gco:aName>
                <gco:CharacterString>Date</gco:CharacterString>
              </gco:aName>
            </gco:TypeName>
          </gfc:valueType>
        </gfc:FC_FeatureAttribute>
      </gfc:carrierOfCharacteristics>
      <gfc:carrierOfCharacteristics>
        <gfc:FC_FeatureAttribute>
          <gfc:memberName>
            <gco:LocalName>Copyright</gco:LocalName>
          </gfc:memberName>
          <gfc:definition>
            <gco:CharacterString>Name of the copyright holder (ENP-China - ERC grant 788476)</gco:CharacterString>
          </gfc:definition>
          <gfc:cardinality gco:nilReason="unknown"/>
          <gfc:valueType>
            <gco:TypeName>
              <gco:aName>
                <gco:CharacterString>String</gco:CharacterString>
              </gco:aName>
            </gco:TypeName>
          </gfc:valueType>
        </gfc:FC_FeatureAttribute>
      </gfc:carrierOfCharacteristics>
      <gfc:carrierOfCharacteristics>
        <gfc:FC_FeatureAttribute>
          <gfc:memberName>
            <gco:LocalName>License</gco:LocalName>
          </gfc:memberName>
          <gfc:definition>
            <gco:CharacterString>Creative Commons License CC0 1.0 Universal </gco:CharacterString>
          </gfc:definition>
          <gfc:cardinality gco:nilReason="unknown"/>
          <gfc:valueType>
            <gco:TypeName>
              <gco:aName>
                <gco:CharacterString>String</gco:CharacterString>
              </gco:aName>
            </gco:TypeName>
          </gfc:valueType>
        </gfc:FC_FeatureAttribute>
      </gfc:carrierOfCharacteristics>
      <gfc:carrierOfCharacteristics>
        <gfc:FC_FeatureAttribute>
          <gfc:memberName>
            <gco:LocalName>Creator</gco:LocalName>
          </gfc:memberName>
          <gfc:cardinality gco:nilReason="unknown"/>
          <gfc:valueType>
            <gco:TypeName>
              <gco:aName>
                <gco:CharacterString>String</gco:CharacterString>
              </gco:aName>
            </gco:TypeName>
          </gfc:valueType>
        </gfc:FC_FeatureAttribute>
      </gfc:carrierOfCharacteristics>
    </gfc:FC_FeatureType>
  </gfc:featureType>
</gfc:FC_FeatureCatalogue>
