{
  "id": "stanford-nn284vs6914",
  "dct_title_s": "Tabulam hanc Aegypti, si æquus ac Diligens Lector, cum Alys, quæ Hactenus Prodicūt",
  "dct_description_sm": [
    "Relief shown pictorially.",
    "Bar scale on map given in \"Milliarium Italica.\"",
    "Index: Explicatio notarum tabulæ Aegypti.",
    "Decorative cartouche, compass rose, ships, sea monsters and other fauna.",
    "Shows topography, vegetation, small bird's eye views of cities, waterways, ports.",
    "Lower and upper halves of map appear separately, each with a containing border.",
    "Appears in Bry's Petits voyages, part I, 1606."
  ],
  "dct_language_sm": [
    "lat"
  ],
  "dct_creator_sm": [
    "Bry, Theodor de, 1528-1598",
    "Pigafetta, Antonio, approximately 1480-approximately 1534",
    "Richter, Wolfgang, -1626"
  ],
  "dct_publisher_sm": [
    "Excudebat W. Richter, impensis I. T. & I. I. de Bry"
  ],
  "dct_issued_s": "1606]",
  "dct_subject_sm": [
    "Maps"
  ],
  "dct_spatial_sm": [
    "Africa",
    "Africa, Southern",
    "Congo River Valley",
    "Madagascar"
  ],
  "schema_provider_s": "Stanford",
  "dct_identifier_sm": [
    "https://purl.stanford.edu/nn284vs6914"
  ],
  "gbl_georeferenced_b": false,
  "gbl_resourceClass_sm": [
    "Maps"
  ],
  "dct_format_s": "JPEG2000",
  "locn_geometry": "ENVELOPE(1.9333333333333333, 52.78333333333333, -0.9166666666666666, -35.88333333333333)",
  "dcat_bbox": "ENVELOPE(1.9333333333333333, 52.78333333333333, -0.9166666666666666, -35.88333333333333)",
  "pcdm_memberOf_sm": [
    "stanford-sr605np6062"
  ],
  "dct_rights_sm": [
    "Images from the The Renaissance Exploration Collection courtesy Stanford University Libraries. This item is in the public domain. There are no restrictions on use. If you have questions, please contact the David Rumsey Map Center at rumseymapcenter@stanford.edu."
  ],
  "dct_rightsHolder_sm": [
    "This work has been identified as being free of known restrictions under copyright law, including all related and neighboring rights. You can copy, modify, distribute and perform the work, even for commercial purposes, all without asking permission."
  ],
  "dct_license_sm": [
    "https://creativecommons.org/publicdomain/mark/1.0/"
  ],
  "dct_accessRights_s": "Public",
  "gbl_mdModified_dt": "2014-06-10T00:00:00Z",
  "gbl_mdVersion_s": "Aardvark",
  "dct_references_s": "{\"http://schema.org/url\":\"https://purl.stanford.edu/nn284vs6914\",\"http://schema.org/downloadUrl\":[{\"url\":\"https://stacks.stanford.edu/object/nn284vs6914\",\"label\":\"Zipped object\"}],\"https://oembed.com\":\"https://purl.stanford.edu/embed.json?hide_title=true\\u0026url=https%3A%2F%2Fpurl.stanford.edu%2Fnn284vs6914\",\"http://iiif.io/api/presentation#manifest\":\"https://purl.stanford.edu/nn284vs6914/iiif3/manifest\",\"https://schema.org/relatedLink\":\"https://searchworks.stanford.edu/view/a10366714\"}",
  "solr_bboxtype__minX": 1.9333333333333333,
  "solr_bboxtype__minY": -35.88333333333333,
  "solr_bboxtype__maxX": 52.78333333333333,
  "solr_bboxtype__maxY": -0.9166666666666666
}
