{
  "dc_identifier_s": "https://purl.stanford.edu/jq618sp8021",
  "dc_title_s": "Protected Areas Database of the United States (PAD-US)",
  "dc_description_s": "The Gap Analysis Program (GAP) is an element of the U.S. Geological Survey. This collection of data contains shapefiles relating to the location, ownership, and stewardship of protected areas within the United States. Title supplied by cataloger. Website accessed: March 31, 2017. System requirements: Geographic Information Systems (GIS) software that reads ESRI shapefile format.",
  "dc_rights_s": "Public",
  "layer_geom_type_s": "Collection",
  "layer_modified_dt": "2023-10-25T17:48:10Z",
  "dc_language_s": "English",
  "dc_subject_sm": [
    "Open spaces",
    "Marine parks and reserves",
    "Marine resources conservation"
  ],
  "dct_spatial_sm": [
    "United States"
  ],
  "dc_publisher_s": "Gap Analysis Program (U.S.)",
  "dc_creator_sm": [
    "Gap Analysis Program (U.S.)"
  ],
  "geoblacklight_version": "1.0",
  "dct_references_s": "{\"http://schema.org/url\":\"https://purl.stanford.edu/jq618sp8021\",\"http://www.loc.gov/mods/v3\":\"https://purl.stanford.edu/jq618sp8021.mods\"}",
  "solr_geom": "ENVELOPE(-64.35, 144.4, 71.6, -14.75)",
  "layer_slug_s": "stanford-jq618sp8021",
  "dct_provenance_s": "Stanford",
  "stanford_rights_metadata_s": "<rightsMetadata>\n    <access type=\"discover\">\n      <machine>\n        <world/>\n      </machine>\n    </access>\n    <access type=\"read\">\n      <machine>\n        <world/>\n      </machine>\n    </access>\n    <use>\n      <human type=\"useAndReproduction\">This item is in the public domain.  There are no restrictions on use.</human>\n      <license/>\n    </use>\n    <copyright>\n      <human>This work is in the Public Domain, meaning that it is not subject to copyright.</human>\n    </copyright>\n  </rightsMetadata>",
  "stanford_use_and_reproduction_s": "This item is in the public domain.  There are no restrictions on use.",
  "stanford_copyright_s": "This work is in the Public Domain, meaning that it is not subject to copyright.",
  "solr_year_i": 2016
}
