{
  "dc_identifier_s": "http://purl.stanford.edu/yb346mk5715",
  "dc_title_s": "Dioceses, Medieval Europe, ca. 1350",
  "dc_description_s": "Polygons of the boundaries of ca. 750 dioceses across Latin Christendom as they appeared during the fourteenth century. The map excludes dioceses in the Latin East and in parts of eastern Europe whose boundaries are unknown (or were never established).",
  "dc_rights_s": "Public",
  "layer_geom_type_s": "Polygon",
  "layer_modified_dt": "2021-03-09T19:19:12Z",
  "dct_issued_s": "2021",
  "dc_type_s": "Dataset",
  "dc_format_s": "Shapefile",
  "dc_language_s": "English",
  "dc_subject_sm": [
    "Dioceses",
    "Churches",
    "Boundaries",
    "Society"
  ],
  "dct_spatial_sm": [
    "Europe"
  ],
  "dct_temporal_sm": [
    "1300-1399"
  ],
  "dc_publisher_s": "Stanford Digital Repository",
  "dc_creator_sm": [
    "Dorin, Rowan",
    "Romani, Clara",
    "Womack, Claire"
  ],
  "geoblacklight_version": "1.0",
  "dct_references_s": "{\"http://schema.org/url\":\"https://purl.stanford.edu/yb346mk5715\",\"http://www.loc.gov/mods/v3\":\"https://purl.stanford.edu/yb346mk5715.mods\",\"http://schema.org/downloadUrl\":\"https://stacks.stanford.edu/file/druid:yb346mk5715/data.zip\",\"http://www.opengis.net/def/serviceType/ogc/wms\":\"https://geowebservices.stanford.edu/geoserver/wms\",\"http://www.isotc211.org/schemas/2005/gmd/\":\"https://raw.githubusercontent.com/OpenGeoMetadata/edu.stanford.purl/master/yb/346/mk/5715/iso19139.xml\",\"http://www.opengis.net/def/serviceType/ogc/wfs\":\"https://geowebservices.stanford.edu/geoserver/wfs\"}",
  "solr_geom": "ENVELOPE(-46.762208, 34.593077, 68.537014, 34.562242)",
  "layer_slug_s": "stanford-yb346mk5715",
  "layer_id_s": "druid:yb346mk5715",
  "dct_provenance_s": "Stanford",
  "stanford_rights_metadata_s": "<rightsMetadata>\n    <access type=\"discover\">\n      <machine>\n        <world/>\n      </machine>\n    </access>\n    <access type=\"read\">\n      <machine>\n        <world/>\n      </machine>\n    </access>\n    <use>\n      <human type=\"useAndReproduction\">You must give appropriate credit, provide a link to the license, and indicate if changes were made. You may do so in any reasonable manner, but not in any way that suggests the licensor endorses you or your use.</human>\n      <human type=\"creativeCommons\">Attribution 3.0 Unported</human>\n      <machine type=\"creativeCommons\">by</machine>\n    </use>\n  </rightsMetadata>",
  "solr_year_i": 1300,
  "dc_source_sm": [
    "stanford-ds112yt9877"
  ],
  "dct_isPartOf_sm": [
    "Digital Atlas of Dioceses and Ecclesiastical Provinces in Late Medieval Europe (1200-1500)"
  ]
}
