{
  "id": "stanford-hv461tq9992",
  "dct_title_s": "Parigi [Paris]",
  "dct_description_sm": [
    "Natal Bonifacio da Sibenicco.",
    "Relief shown pictorially.",
    "North oriented at a 45° angle between top and right of sheet.",
    "Index of city place names in lower right.",
    "\"Levante\" [east] at bottom of sheet.",
    "Decorative carouches, compass rose, coat of arms (\"Arma della citta di Parigi\").",
    "Siege map of Paris showing walls disposition of forces, e.g. artillery, soldiers.",
    "Appears in Pigafetta's Relatione dell' Assidio de Parigi, 1591."
  ],
  "dct_language_sm": [
    "lat"
  ],
  "dct_creator_sm": [
    "Pigafetta, Filippo, 1533-1604",
    "Bonifacio, Natale, 1538-1592",
    "Grassi, Bartolomeo, active 1582-1600"
  ],
  "dct_publisher_sm": [
    "Appresso Bartolomeo Grassi"
  ],
  "dct_issued_s": "1591",
  "dct_spatial_sm": [
    "Europe",
    "Paris (France)"
  ],
  "schema_provider_s": "Stanford",
  "dct_identifier_sm": [
    "https://purl.stanford.edu/hv461tq9992"
  ],
  "gbl_georeferenced_b": false,
  "gbl_resourceClass_sm": [
    "Maps"
  ],
  "dct_format_s": "JPEG2000",
  "locn_geometry": "ENVELOPE(2.156111111111111, 2.528611111111111, 48.95527777777778, 48.75805555555556)",
  "dcat_bbox": "ENVELOPE(2.156111111111111, 2.528611111111111, 48.95527777777778, 48.75805555555556)",
  "pcdm_memberOf_sm": [
    "stanford-sr605np6062"
  ],
  "dct_rights_sm": [
    "Images from the The Renaissance Exploration Collection courtesy Stanford University Libraries. This item is in the public domain. There are no restrictions on use. If you have questions, please contact the David Rumsey Map Center at rumseymapcenter@stanford.edu."
  ],
  "dct_rightsHolder_sm": [
    "This work has been identified as being free of known restrictions under copyright law, including all related and neighboring rights. You can copy, modify, distribute and perform the work, even for commercial purposes, all without asking permission."
  ],
  "dct_license_sm": [
    "https://creativecommons.org/publicdomain/mark/1.0/"
  ],
  "dct_accessRights_s": "Public",
  "gbl_mdModified_dt": "2014-02-18T00:00:00Z",
  "gbl_mdVersion_s": "Aardvark",
  "dct_references_s": "{\"http://schema.org/url\":\"https://purl.stanford.edu/hv461tq9992\",\"http://schema.org/downloadUrl\":[{\"url\":\"https://stacks.stanford.edu/object/hv461tq9992\",\"label\":\"Zipped object\"}],\"https://oembed.com\":\"https://purl.stanford.edu/embed.json?hide_title=true\\u0026url=https%3A%2F%2Fpurl.stanford.edu%2Fhv461tq9992\",\"http://iiif.io/api/presentation#manifest\":\"https://purl.stanford.edu/hv461tq9992/iiif3/manifest\",\"https://schema.org/relatedLink\":\"https://searchworks.stanford.edu/view/a10366590\"}",
  "solr_bboxtype__minX": 2.156111111111111,
  "solr_bboxtype__minY": 48.75805555555556,
  "solr_bboxtype__maxX": 2.528611111111111,
  "solr_bboxtype__maxY": 48.95527777777778
}
