{
  "dc_identifier_s": "http://purl.stanford.edu/zj068kg9781",
  "dc_title_s": "Groundwater Elevation Change, California, Fall 2010 to Fall 2015",
  "dc_description_s": "This point shapefile represents changes in groundwater levels in California. These data represent groundwater changes between fall 2010 and fall 2015. Each point shows the calculated difference between the measured groundwater levels from the time period. The change in groundwater level is plotted on the map only if a measurement exists in both time periods as well. The colored points in the measurements layer show the location of all wells where the groundwater level change is determined. This layer is intended to be used as a compliment to data, reports, and other information provided by the California Groundwater Information Center.",
  "dc_rights_s": "Public",
  "dct_provenance_s": "Stanford",
  "dct_references_s": "{\"http://schema.org/url\":\"http://purl.stanford.edu/zj068kg9781\",\"http://schema.org/downloadUrl\":\"http://stacks.stanford.edu/file/druid:zj068kg9781/data.zip\",\"http://www.loc.gov/mods/v3\":\"http://purl.stanford.edu/zj068kg9781.mods\",\"http://www.isotc211.org/schemas/2005/gmd/\":\"https://raw.githubusercontent.com/OpenGeoMetadata/edu.stanford.purl/master/zj/068/kg/9781/iso19139.xml\",\"http://www.opengis.net/def/serviceType/ogc/wfs\":\"https://geowebservices.stanford.edu/geoserver/wfs\",\"http://www.opengis.net/def/serviceType/ogc/wms\":\"https://geowebservices.stanford.edu/geoserver/wms\"}",
  "layer_id_s": "druid:zj068kg9781",
  "layer_slug_s": "stanford-zj068kg9781",
  "layer_geom_type_s": "Point",
  "layer_modified_dt": "2017-02-10T00:44:23Z",
  "dc_format_s": "Shapefile",
  "dc_language_s": "English",
  "dc_type_s": "Dataset",
  "dc_publisher_s": "California. Department of Water Resources",
  "dc_creator_sm": [
    "California. Department of Water Resources"
  ],
  "dc_subject_sm": [
    "Hydrogeology",
    "Groundwater",
    "Basins (Geology)",
    "Inland Waters",
    "Geoscientific Information",
    "Elevation"
  ],
  "dct_issued_s": "2016",
  "dct_temporal_sm": [
    "2010-2015"
  ],
  "dct_spatial_sm": [
    "California"
  ],
  "solr_geom": "ENVELOPE(-124.2696, -116.350479, 42.012741, 33.236679)",
  "solr_year_i": 2010,
  "stanford_rights_metadata_s": "<?xml version=\"1.0\"?>\n<rightsMetadata>\n  <access type=\"discover\">\n    <machine>\n      <world/>\n    </machine>\n  </access>\n  <access type=\"read\">\n    <machine>\n      <world/>\n    </machine>\n  </access>\n  <use>\n    <human type=\"useAndReproduction\">This item is in the public domain.  There are no restrictions on use.</human>\n    <human type=\"creativeCommons\"/>\n    <machine type=\"creativeCommons\"/>\n  </use>\n  <copyright>\n    <human>This work is in the Public Domain, meaning that it is not subject to copyright.</human>\n  </copyright>\n</rightsMetadata>\n",
  "geoblacklight_version": "1.0"
}