{
  "id": "stanford-wk440gb6519",
  "dct_title_s": "Bacon's bird's-eye view of South Africa with enlarged views of Natal, and Mafeking to Pretoria",
  "dct_description_sm": [
    "Map torn along folds into 5 pieces."
  ],
  "dct_language_sm": [
    "eng"
  ],
  "dct_publisher_sm": [
    "G. W. Bacon & Co., Ltd., 127, Strand"
  ],
  "dct_issued_s": "1900",
  "dct_spatial_sm": [
    "Africa",
    "South Africa"
  ],
  "schema_provider_s": "Stanford",
  "dct_identifier_sm": [
    "https://purl.stanford.edu/wk440gb6519"
  ],
  "gbl_georeferenced_b": false,
  "gbl_resourceClass_sm": [
    "Maps"
  ],
  "dct_format_s": "JPEG2000",
  "locn_geometry": "ENVELOPE(14.3, 33.28333333333333, -22.2, -35.11666666666667)",
  "dcat_bbox": "ENVELOPE(14.3, 33.28333333333333, -22.2, -35.11666666666667)",
  "pcdm_memberOf_sm": [
    "stanford-pr739kw7087"
  ],
  "dct_rights_sm": [
    "Image courtesy University of Cape Town Libraries, Special Collections: Maps scanned under the William and Yvonne Jacobson Digital Africana Program at UCT. If you have questions, please contact David Rumsey Map Center at rumseymapcenter@stanford.edu."
  ],
  "dct_rightsHolder_sm": [
    "Property rights reside with the repository. Copyright (c) Stanford University. All Rights Reserved."
  ],
  "dct_license_sm": [
    "https://creativecommons.org/licenses/by-nc/3.0/legalcode"
  ],
  "dct_accessRights_s": "Public",
  "gbl_mdModified_dt": "2022-08-23T18:38:47Z",
  "gbl_mdVersion_s": "Aardvark",
  "dct_references_s": "{\"http://schema.org/url\":\"https://purl.stanford.edu/wk440gb6519\",\"http://schema.org/downloadUrl\":[{\"url\":\"https://stacks.stanford.edu/object/wk440gb6519\",\"label\":\"Zipped object\"}],\"https://oembed.com\":\"https://purl.stanford.edu/embed.json?hide_title=true\\u0026url=https%3A%2F%2Fpurl.stanford.edu%2Fwk440gb6519\",\"http://iiif.io/api/presentation#manifest\":\"https://purl.stanford.edu/wk440gb6519/iiif3/manifest\",\"https://schema.org/relatedLink\":\"https://searchworks.stanford.edu/view/wk440gb6519\"}"
}
