{
  "id": "stanford-gz586hz0366",
  "dct_title_s": "Greenwich Bay, Rhode Island",
  "dct_description_sm": [
    "triangulation by A.M. Harrison in 1863 ; topography [by A.M. Harrison] in 1867 and '68 ; hydrography by F.P. Webber in 1867 ; verified, J.E. Hilgard.",
    "Depths shown by soundings.",
    "Includes notes on soundings and tides.",
    "\"No. 351\"--Upper left margin.",
    "\"Plate no. 1111\"--Upper margin."
  ],
  "dct_language_sm": [
    "eng"
  ],
  "dct_creator_sm": [
    "Harrison, A. M. (Alexander Medina), 1829-1881",
    "Hilgard, J. E. (Julius Erasmus), 1825-1891"
  ],
  "dct_publisher_sm": [
    "Coast Survey Office"
  ],
  "dct_issued_s": "1867 [i.e. 1888]",
  "dct_subject_sm": [
    "Nautical charts"
  ],
  "dct_spatial_sm": [
    "Rhode Island",
    "Greenwich Bay",
    "Greenwich Bay (R.I.)"
  ],
  "dcat_theme_sm": [
    "Imagery"
  ],
  "schema_provider_s": "Stanford",
  "dct_identifier_sm": [
    "https://purl.stanford.edu/gz586hz0366"
  ],
  "gbl_georeferenced_b": false,
  "gbl_resourceClass_sm": [
    "Maps"
  ],
  "dct_format_s": "JPEG2000",
  "locn_geometry": "ENVELOPE(-71.46666666666667, -71.36666666666666, 41.7, 41.65)",
  "dcat_bbox": "ENVELOPE(-71.46666666666667, -71.36666666666666, 41.7, 41.65)",
  "dct_rights_sm": [
    "Image from the Map Collections courtesy Stanford University Libraries. This item is in the public domain. There are no restrictions on use. If you have questions, please contact Branner Earth Sciences Library & Map Collections at brannerlibrary@stanford.edu."
  ],
  "dct_rightsHolder_sm": [
    "This work has been identified as being free of known restrictions under copyright law, including all related and neighboring rights. You can copy, modify, distribute and perform the work, even for commercial purposes, all without asking permission."
  ],
  "dct_license_sm": [
    "https://creativecommons.org/publicdomain/mark/1.0/"
  ],
  "dct_accessRights_s": "Public",
  "gbl_mdModified_dt": "2005-10-18T00:00:00Z",
  "gbl_mdVersion_s": "Aardvark",
  "dct_references_s": "{\"http://schema.org/url\":\"https://purl.stanford.edu/gz586hz0366\",\"http://schema.org/downloadUrl\":[{\"url\":\"https://stacks.stanford.edu/object/gz586hz0366\",\"label\":\"Zipped object\"}],\"https://oembed.com\":\"https://purl.stanford.edu/embed.json?hide_title=true\\u0026url=https%3A%2F%2Fpurl.stanford.edu%2Fgz586hz0366\",\"http://iiif.io/api/presentation#manifest\":\"https://purl.stanford.edu/gz586hz0366/iiif3/manifest\",\"https://schema.org/relatedLink\":\"https://searchworks.stanford.edu/view/a8669781\"}"
}
