{
  "id": "stanford-hq256mh7217",
  "dct_title_s": "Uganda city maps, 1:12,500",
  "dct_alternative_sm": [
    "Kampala",
    "Series Y932"
  ],
  "dct_description_sm": [
    "prepared and published under the direction of the Defense Mapping Agency Hydrographic-Topographic Center.",
    "Relief shown by contours and hachures. Contour interval 10 feet.",
    "\"Map information as of 1987.\"",
    "\"DMA STOCK NO. Y932XKAMPALA.\"",
    "Includes indexes, text, location and boundaries maps, and guide to numbered features."
  ],
  "dct_language_sm": [
    "eng"
  ],
  "dct_creator_sm": [
    "United States, Defense Mapping Agency., Hydrographic/Topographic Center."
  ],
  "dct_publisher_sm": [
    "The Agency"
  ],
  "dct_issued_s": "1994",
  "dct_spatial_sm": [
    "Kampala (Uganda)"
  ],
  "schema_provider_s": "Stanford",
  "dct_identifier_sm": [
    "https://purl.stanford.edu/hq256mh7217"
  ],
  "gbl_georeferenced_b": false,
  "gbl_resourceClass_sm": [
    "Maps"
  ],
  "dct_format_s": "JPEG2000",
  "locn_geometry": "ENVELOPE(32.56305555555555, 32.66305555555555, 2.354166666666667, 0.28055555555555556)",
  "dcat_bbox": "ENVELOPE(32.56305555555555, 32.66305555555555, 2.354166666666667, 0.28055555555555556)",
  "dct_rights_sm": [
    "Image from the Map Collections courtesy Stanford University Libraries. This item is in the public domain. There are no restrictions on use. If you have questions, please contact Branner Earth Sciences Library & Map Collections at brannerlibrary@stanford.edu."
  ],
  "dct_rightsHolder_sm": [
    "This work has been identified as being free of known restrictions under copyright law, including all related and neighboring rights. You can copy, modify, distribute and perform the work, even for commercial purposes, all without asking permission."
  ],
  "dct_license_sm": [
    "https://creativecommons.org/publicdomain/mark/1.0/"
  ],
  "dct_accessRights_s": "Public",
  "gbl_mdModified_dt": "2002-05-24T00:00:00Z",
  "gbl_mdVersion_s": "Aardvark",
  "dct_references_s": "{\"http://schema.org/url\":\"https://purl.stanford.edu/hq256mh7217\",\"http://schema.org/downloadUrl\":[{\"url\":\"https://stacks.stanford.edu/object/hq256mh7217\",\"label\":\"Zipped object\"}],\"https://oembed.com\":\"https://purl.stanford.edu/embed.json?hide_title=true\\u0026url=https%3A%2F%2Fpurl.stanford.edu%2Fhq256mh7217\",\"http://iiif.io/api/presentation#manifest\":\"https://purl.stanford.edu/hq256mh7217/iiif3/manifest\",\"https://schema.org/relatedLink\":\"https://searchworks.stanford.edu/view/a6995290\"}"
}
