{
  "id": "stanford-zk406hx4414",
  "dct_title_s": "Denmark & South Scandinavia",
  "dct_description_sm": [
    "Stanford's Geographical Estabt. ; London : Longmans & Co. Paternoster Row.",
    "Relief shown by hachures, spot heights, and coloring.",
    "\"Land below 1000 feet coloured green / land above 1000 feet coloured brown.\"",
    "Longitudinal and latitudinal lines (Greenwich meridian).",
    "Shows boundaries, cities, waterways, low water (100 fathom line), roads.",
    "In margin: \"11.\"",
    "Few additional details compared to 1889 map, along with presence of Kiel Canal (\"North Sea & Baltic ship canal\" on map) date this map to late 1890s. Denmark-German boundary predates Schleswig referendum in 1920."
  ],
  "dct_language_sm": [
    "eng"
  ],
  "dct_publisher_sm": [
    "Longmans & Co.,"
  ],
  "dct_issued_s": "[between 1895 and 1905?]",
  "dct_spatial_sm": [
    "Denmark",
    "Scandinavia"
  ],
  "schema_provider_s": "Stanford",
  "dct_identifier_sm": [
    "https://purl.stanford.edu/zk406hx4414"
  ],
  "gbl_georeferenced_b": false,
  "gbl_resourceClass_sm": [
    "Maps"
  ],
  "dct_format_s": "JPEG2000",
  "locn_geometry": "ENVELOPE(4.05, 20.3, 64.1, 53.266666666666666)",
  "dcat_bbox": "ENVELOPE(4.05, 20.3, 64.1, 53.266666666666666)",
  "dct_rights_sm": [
    "Image from the Map Collections courtesy Stanford University Libraries. This item is in the public domain. There are no restrictions on use. If you have questions, please contact Branner Earth Sciences Library & Map Collections at brannerlibrary@stanford.edu."
  ],
  "dct_rightsHolder_sm": [
    "This work has been identified as being free of known restrictions under copyright law, including all related and neighboring rights. You can copy, modify, distribute and perform the work, even for commercial purposes, all without asking permission."
  ],
  "dct_license_sm": [
    "https://creativecommons.org/publicdomain/mark/1.0/"
  ],
  "dct_accessRights_s": "Public",
  "gbl_mdModified_dt": "2017-05-20T01:19:37Z",
  "gbl_mdVersion_s": "Aardvark",
  "dct_references_s": "{\"http://schema.org/url\":\"https://purl.stanford.edu/zk406hx4414\",\"http://schema.org/downloadUrl\":[{\"url\":\"https://stacks.stanford.edu/object/zk406hx4414\",\"label\":\"Zipped object\"}],\"https://oembed.com\":\"https://purl.stanford.edu/embed.json?hide_title=true\\u0026url=https%3A%2F%2Fpurl.stanford.edu%2Fzk406hx4414\",\"http://iiif.io/api/presentation#manifest\":\"https://purl.stanford.edu/zk406hx4414/iiif3/manifest\",\"https://schema.org/relatedLink\":\"https://searchworks.stanford.edu/view/a12002560\"}",
  "solr_bboxtype__minX": 4.05,
  "solr_bboxtype__minY": 53.266666666666666,
  "solr_bboxtype__maxX": 20.3,
  "solr_bboxtype__maxY": 64.1
}
